AUTHORS
CHANGELOG
LICENSE
MANIFEST.in
README
THANKS
TODO
setup.py
Cellulose.egg-info/PKG-INFO
Cellulose.egg-info/SOURCES.html
Cellulose.egg-info/SOURCES.txt
Cellulose.egg-info/dependency_links.html
Cellulose.egg-info/dependency_links.txt
Cellulose.egg-info/top_level.html
Cellulose.egg-info/top_level.txt
Cellulose.egg-info/zip-safe
cellulose/__init__.py
cellulose/cells.py
cellulose/celltypes.py
cellulose/descriptors.py
cellulose/observers.py
cellulose/extra/__init__.py
cellulose/extra/restrictions.py
docs/algorithm.txt
docs/tutorial.txt
tests/celltests.py
