Metadata-Version: 1.0
Name: Cellulose
Version: 0.2
Summary: A mechanism for maintaining consistency betweeninter-dependant values with caching and lazy evaluation.
Home-page: UNKNOWN
Author: Matthew Marshall
Author-email: matthew@matthewmarshall.org
License: BSD
Keywords: cellulose dependency discovery lazy evaluation caching
Platform: UNKNOWN
